README.txt
setup.cfg
setup.py
algoviz/__init__.py
algoviz/vizlist.py
algoviz.egg-info/PKG-INFO
algoviz.egg-info/SOURCES.txt
algoviz.egg-info/dependency_links.txt
algoviz.egg-info/requires.txt
algoviz.egg-info/top_level.txt