Metadata-Version: 2.1
Name: algoviz
Version: 0.1.6
Summary: Generates visualizations for arrays
Home-page: https://github.com/algometrix/algoviz
Author: Ashish Nagar
Author-email: ashishnagar31@gmail.com
License: MIT
Download-URL: https://github.com/algometrix/algoviz/archive/v_0.1.2.tar.gz
Keywords: Visualization,Algorithms
Platform: UNKNOWN
Classifier: Development Status :: 3 - Alpha
Classifier: Intended Audience :: Developers
Classifier: Topic :: Software Development :: Build Tools
Classifier: License :: OSI Approved :: MIT License
Classifier: Programming Language :: Python :: 3.7
Classifier: Programming Language :: Python :: 3.8
